LICENSE
README.md
setup.cfg
setup.py
multiverseML.egg-info/PKG-INFO
multiverseML.egg-info/SOURCES.txt
multiverseML.egg-info/dependency_links.txt
multiverseML.egg-info/requires.txt
multiverseML.egg-info/top_level.txt
multiverseml/__init__.py
multiverseml/multiverseml.py